<?xml version="1.0" encoding="UTF-8" ?>
<!DOCTYPE generatorConfiguration PUBLIC "-//mybatis.org//DTD MyBatis Generator Configuration 1.0//EN"
        "http://mybatis.org/dtd/mybatis-generator-config_1_0.dtd" >
<generatorConfiguration>
	<!-- 数据库驱动 注意：这个 location要指明\MySQL-connector-Java jar包的绝对路径 -->
	<classPathEntry
		location="D:\software\IDE\Repository\mysql\mysql-connector-java\5.1.42\mysql-connector-java-5.1.42.jar" />

	<context id="marketing" targetRuntime="MyBatis3"
		defaultModelType="flat">
		<property name="javaFileEncoding" value="UTF-8" />

		<!-- 配置生成toString()方法 -->
		<plugin type="org.mybatis.generator.plugins.ToStringPlugin" />

		<commentGenerator>
			<!-- 是否禁止显示日期 true：是 ： false:否 -->
			<property name="suppressDate" value="false" />
			<!-- 是否去除自动生成的所有注释 true：是 ： false:否 -->
			<property name="suppressAllComments" value="false" />
			<!-- 是否添加字段注释 true:是 false：否 -->
			<property name="addRemarkComments" value="true" />
			<!-- 自定义属性 作者名称 -->
			<property name="author" value="Jeff" />
		</commentGenerator>

		<!--数据库链接URL，用户名、密码 -->
		<jdbcConnection driverClass="com.mysql.jdbc.Driver"
			connectionURL="jdbc:mysql://192.168.31.91:3306/env_enforce" 
			userId="root"
			password="root">
		</jdbcConnection>

		<javaTypeResolver>
			<property name="forceBigDecimals" value="false" />
		</javaTypeResolver>

		<!-- 配置生成实体类的包名和位置 -->
		<javaModelGenerator targetPackage="model"
			targetProject="mybatis3">
			<property name="enableSubPackages" value="true" />
			<property name="trimStrings" value="true" />
		</javaModelGenerator>
		
		<!-- 配置生成映射文件的包名和位置 -->
		<sqlMapGenerator targetPackage="mapperXml"
			targetProject="mybatis3">
			<property name="enableSubPackages" value="true" />
		</sqlMapGenerator>
		
		<!-- 配置生成mapper文件的包名和位置 -->
		<javaClientGenerator type="XMLMAPPER"
			targetPackage="mapper" targetProject="mybatis3">
			<property name="enableSubPackages" value="true" />
		</javaClientGenerator>
		
		<!-- 配置需要反向生成表的信息 -->
		<table tableName="region" domainObjectName="Region"
			enableCountByExample="false" enableUpdateByExample="false"
			enableDeleteByExample="false" enableSelectByExample="false"
			selectByExampleQueryId="false">
			<property name="ignoreQualifiersAtRuntime" value="true" />
			<generatedKey column="id" sqlStatement="MySql" identity="true" />
		</table>
	</context>
</generatorConfiguration>